<?xml version="1.0" encoding="UTF-8"?>
<!--
     IBM Omni driver
     Copyright (c) International Business Machines Corp., 2000

     This library is free software; you can redistribute it and/or modify
     it under the terms of the GNU Lesser General Public License as published
     by the Free Software Foundation; either version 2.1 of the License, or
     (at your option) any later version.

     This library is distributed in the hope that it will be useful,
     but WITHOUT ANY WARRANTY; without even the implied warranty of
     MERCHANTABILITY or FITNESS FOR A PARTICULAR PURPOSE.  See
     the GNU Lesser General Public License for more details.

     You should have received a copy of the GNU Lesser General Public License
     along with this library; if not, write to the Free Software
     Foundation, Inc., 59 Temple Place, Suite 330, Boston, MA 02111-1307 USA
-->
<deviceForms xmlns="http://www.ibm.com/linux/ltc/projects/omni/" xmlns:xs="http://www.w3.org/2001/XMLSchema-instance" xs:schemaLocation="http://www.ibm.com/linux/ltc/projects/omni/ ../OmniDevice.xsd">
   <deviceForm>
      <name>iso_a4_210.00x297.00mm</name>
      <omniName>FORM_A4</omniName>
      <formCapabilities>NO_CAPABILITIES</formCapabilities>
      <command>_ESC_ "~8" _NUL_ HEX (09) HEX (01) HEX (8C) HEX (01) HEX (8C) HEX (2B) HEX (67) HEX (3E) HEX (AC) HEX (02)</command>
      <hardCopyCap>
         <hardCopyCapLeft>7000</hardCopyCapLeft>
         <hardCopyCapTop>7000</hardCopyCapTop>
         <hardCopyCapRight>7000</hardCopyCapRight>
         <hardCopyCapBottom>7000</hardCopyCapBottom>
      </hardCopyCap>
   </deviceForm>
   <deviceForm>
      <name>iso_a3_297.00x420.00mm</name>
      <omniName>FORM_A3</omniName>
      <formCapabilities>NO_CAPABILITIES</formCapabilities>
      <command>_ESC_ "~8" _NUL_ HEX (09) HEX (01) HEX (8C) HEX (01) HEX (8C) HEX (3E) HEX (AC) HEX (59) HEX (E9) HEX (02)</command>
      <hardCopyCap>
         <hardCopyCapLeft>7000</hardCopyCapLeft>
         <hardCopyCapTop>7000</hardCopyCapTop>
         <hardCopyCapRight>7000</hardCopyCapRight>
         <hardCopyCapBottom>7000</hardCopyCapBottom>
      </hardCopyCap>
   </deviceForm>
   <deviceForm>
      <name>iso_a5_148.00x210.00mm</name>
      <omniName>FORM_A5</omniName>
      <formCapabilities>NO_CAPABILITIES</formCapabilities>
      <command>_ESC_ "~8" _NUL_ HEX (09) HEX (01) HEX (8C) HEX (01) HEX (8C) HEX (1D) HEX (AC) HEX (2B) HEX (67) HEX (02)</command>
      <hardCopyCap>
         <hardCopyCapLeft>7000</hardCopyCapLeft>
         <hardCopyCapTop>7000</hardCopyCapTop>
         <hardCopyCapRight>7000</hardCopyCapRight>
         <hardCopyCapBottom>7000</hardCopyCapBottom>
      </hardCopyCap>
   </deviceForm>
   <deviceForm>
      <name>jis_b4_257.00x364.00mm</name>
      <omniName>FORM_JIS_B4</omniName>
      <formCapabilities>NO_CAPABILITIES</formCapabilities>
      <command>_ESC_ "~8" _NUL_ HEX (09) HEX (01) HEX (8C) HEX (01) HEX (8C) HEX (35) HEX (D0) HEX (4D) HEX (82) HEX (02)</command>
      <hardCopyCap>
         <hardCopyCapLeft>7000</hardCopyCapLeft>
         <hardCopyCapTop>7000</hardCopyCapTop>
         <hardCopyCapRight>7000</hardCopyCapRight>
         <hardCopyCapBottom>7000</hardCopyCapBottom>
      </hardCopyCap>
   </deviceForm>
   <deviceForm>
      <name>jis_b5_182.00x257.00mm</name>
      <omniName>FORM_JIS_B5</omniName>
      <formCapabilities>NO_CAPABILITIES</formCapabilities>
      <command>_ESC_ "~8" _NUL_ HEX (09) HEX (01) HEX (8C) HEX (01) HEX (8C) HEX (25) HEX (34) HEX (35) HEX (D0) HEX (02)</command>
      <hardCopyCap>
         <hardCopyCapLeft>7000</hardCopyCapLeft>
         <hardCopyCapTop>7000</hardCopyCapTop>
         <hardCopyCapRight>7000</hardCopyCapRight>
         <hardCopyCapBottom>7000</hardCopyCapBottom>
      </hardCopyCap>
   </deviceForm>
   <deviceForm>
      <name>jis_b6_128.00x182.00mm</name>
      <omniName>FORM_JIS_B6</omniName>
      <formCapabilities>NO_CAPABILITIES</formCapabilities>
      <command>_ESC_ "~8" _NUL_ HEX (09) HEX (01) HEX (8C) HEX (01) HEX (8C) HEX (19) HEX (3E) HEX (25) HEX (34) HEX (02)</command>
      <hardCopyCap>
         <hardCopyCapLeft>7000</hardCopyCapLeft>
         <hardCopyCapTop>7000</hardCopyCapTop>
         <hardCopyCapRight>7000</hardCopyCapRight>
         <hardCopyCapBottom>7000</hardCopyCapBottom>
      </hardCopyCap>
   </deviceForm>
   <deviceForm>
      <name>na_letter_8.50x11.00in</name>
      <omniName>FORM_LETTER</omniName>
      <formCapabilities>NO_CAPABILITIES</formCapabilities>
      <command>_ESC_ "~8" _NUL_ HEX (09) HEX (01) HEX (8C) HEX (01) HEX (8C) HEX (2C) HEX (B6) HEX (3A) HEX (C6) HEX (02)</command>
      <hardCopyCap>
         <hardCopyCapLeft>7000</hardCopyCapLeft>
         <hardCopyCapTop>7000</hardCopyCapTop>
         <hardCopyCapRight>7000</hardCopyCapRight>
         <hardCopyCapBottom>7000</hardCopyCapBottom>
      </hardCopyCap>
   </deviceForm>
   <deviceForm>
      <name>na_legal_8.50x14.00in</name>
      <omniName>FORM_LEGAL</omniName>
      <formCapabilities>NO_CAPABILITIES</formCapabilities>
      <command>_ESC_ "~8" _NUL_ HEX (09) HEX (01) HEX (8C) HEX (01) HEX (8C) HEX (2C) HEX (B6) HEX (4B) HEX (A6) HEX (02)</command>
      <hardCopyCap>
         <hardCopyCapLeft>7000</hardCopyCapLeft>
         <hardCopyCapTop>7000</hardCopyCapTop>
         <hardCopyCapRight>7000</hardCopyCapRight>
         <hardCopyCapBottom>7000</hardCopyCapBottom>
      </hardCopyCap>
   </deviceForm>
   <deviceForm>
      <name>na_tabloid_11.00x17.00in</name>
      <omniName>FORM_TABLOID</omniName>
      <formCapabilities>NO_CAPABILITIES</formCapabilities>
      <command>_ESC_ "~8" _NUL_ HEX (09) HEX (01) HEX (8C) HEX (01) HEX (8C) HEX (3A) HEX (C6) HEX (5C) HEX (86) HEX (02)</command>
     <hardCopyCap>
         <hardCopyCapLeft>7000</hardCopyCapLeft>
         <hardCopyCapTop>7000</hardCopyCapTop>
         <hardCopyCapRight>7000</hardCopyCapRight>
         <hardCopyCapBottom>7000</hardCopyCapBottom>
      </hardCopyCap>
   </deviceForm>
</deviceForms>
