<?xml version="1.0" encoding="UTF-8"?>
<!--
     IBM Omni driver
     Copyright (c) International Business Machines Corp., 2000

     This library is free software; you can redistribute it and/or modify
     it under the terms of the GNU Lesser General Public License as published
     by the Free Software Foundation; either version 2.1 of the License, or
     (at your option) any later version.

     This library is distributed in the hope that it will be useful,
     but WITHOUT ANY WARRANTY; without even the implied warranty of
     MERCHANTABILITY or FITNESS FOR A PARTICULAR PURPOSE.  See
     the GNU Lesser General Public License for more details.

     You should have received a copy of the GNU Lesser General Public License
     along with this library; if not, write to the Free Software
     Foundation, Inc., 59 Temple Place, Suite 330, Boston, MA 02111-1307 USA
-->
<Device xmlns="http://www.ibm.com/linux/ltc/projects/omni/" xmlns:xs="http://www.w3.org/2001/XMLSchema-instance" name="Panasonic KX-P1124" xs:schemaLocation="http://www.ibm.com/linux/ltc/projects/omni/ ../OmniDevice.xsd">
   <DriverName>Panasonic</DriverName>
   <Capability type="COLOR"/>
   <Capability type="MONOCHROME"/>
   <Capability type="MIRROR"/>
   <RasterCapabilities type="TOP_TO_BOTTOM"/>
   <PDL level="PDL_Epson" sublevel="LEVEL_ESC" major="1" minor="0"/>
   <Uses>Panasonic KX-P1123 Commands.xml</Uses>
   <Has>Panasonic Orientations.xml</Has>
   <Has>Panasonic KX-P1123 Resolutions.xml</Has>
   <Has>Panasonic KX-P1124 PrintModes.xml</Has>
   <Has>Panasonic KX-P1123 Trays.xml</Has>
   <Has>Panasonic KX-P1124 Forms.xml</Has>
   <Has>Panasonic KX-P1123 Medias.xml</Has>
   <Has>Panasonic KX-P1123 Connections.xml</Has>
   <Has>Panasonic KX-P1124 Gammas.xml</Has>
   <Has>Panasonic Copies.xml</Has>
   <Has>Panasonic NUps.xml</Has>
   <Has>Panasonic OutputBins.xml</Has>
   <Has>Panasonic Scalings.xml</Has>
   <Has>Panasonic SheetCollates.xml</Has>
   <Has>Panasonic Sides.xml</Has>
   <Has>Panasonic Stitchings.xml</Has>
   <Has>Panasonic Trimmings.xml</Has>
   <Instance>Panasonic ESC Instance.hpp</Instance>
   <Instance>Panasonic ESC Instance.cpp</Instance>
   <Blitter>Panasonic ESC Blitter.hpp</Blitter>
   <Blitter>Panasonic ESC Blitter.cpp</Blitter>
   <DefaultJobProperties>
      <Copies>1</Copies>
      <dither>DITHER_STUCKI_DIFFUSION</dither>
      <Form>na_letter_8.50x11.00in</Form>
      <omniForm>FORM_LETTER</omniForm>
      <media>MEDIA_PLAIN</media>
      <NumberUp>
         <NumberUp FORMAT="XbyY">
            <x>1</x>
            <y>1</y>
         </NumberUp>
         <NumberUpDirection>TorightTobottom</NumberUpDirection>
      </NumberUp>
      <Rotation>Portrait</Rotation>
      <omniOrientation>ORIENTATION_PORTRAIT</omniOrientation>
      <OutputBin>Top</OutputBin>
      <printmode>PRINT_MODE_24_CMYK</printmode>
      <Resolution>180x180</Resolution>
      <omniResolution>RESOLUTION_180_X_180</omniResolution>
      <Scaling>
         <ScalingPercentage>100</ScalingPercentage>
         <ScalingType>None</ScalingType>
      </Scaling>
      <SheetCollate>SheetUncollated</SheetCollate>
      <Sides>OneSidedFront</Sides>
      <Stitching>
         <StitchingPosition>0</StitchingPosition>
         <StitchingReferenceEdge>Top</StitchingReferenceEdge>
         <StitchingType>None</StitchingType>
         <StitchingCount>0</StitchingCount>
         <StitchingAngle>0</StitchingAngle>
      </Stitching>
      <InputTray>Rear</InputTray>
      <omniTray>TRAY_REAR_CONTINUOUS</omniTray>
      <Trimming>None</Trimming>
   </DefaultJobProperties>
</Device>
